[
  {
    "source_id": "student_n06114515",
    "target_id": "major_data_science",
    "relation_type": "STUDIED_MAJOR",
    "weight": 1.0,
    "properties": {}
  },
  {
    "source_id": "student_n06114515",
    "target_id": "course_ifn556_object_oriented_programming",
    "relation_type": "COMPLETED_COURSE",
    "weight": 1.0,
    "properties": {}
  },
  {
    "source_id": "student_n06114515",
    "target_id": "course_ifn563_algorithms_and_complexity",
    "relation_type": "COMPLETED_COURSE",
    "weight": 1.0,
    "properties": {}
  },
  {
    "source_id": "student_n06114515",
    "target_id": "course_ifn555_introduction_to_programming",
    "relation_type": "COMPLETED_COURSE",
    "weight": 1.0,
    "properties": {}
  },
  {
    "source_id": "student_n06114515",
    "target_id": "course_ifn632_advanced_data_analytics",
    "relation_type": "COMPLETED_COURSE",
    "weight": 1.0,
    "properties": {}
  },
  {
    "source_id": "student_n06114515",
    "target_id": "course_ifn551_computer_systems_fundamentals",
    "relation_type": "COMPLETED_COURSE",
    "weight": 1.0,
    "properties": {}
  },
  {
    "source_id": "student_n06114515",
    "target_id": "course_ifn564_machine_learning",
    "relation_type": "COMPLETED_COURSE",
    "weight": 1.0,
    "properties": {}
  },
  {
    "source_id": "student_n06114515",
    "target_id": "course_ifn565_advanced_programming",
    "relation_type": "COMPLETED_COURSE",
    "weight": 1.0,
    "properties": {}
  },
  {
    "source_id": "student_n06114515",
    "target_id": "course_ifn552_systems_analysis_and_design",
    "relation_type": "COMPLETED_COURSE",
    "weight": 1.0,
    "properties": {}
  },
  {
    "source_id": "student_n06114515",
    "target_id": "skill_machine_learning_(scikit-learn,_tensorflow)",
    "relation_type": "HAS_SKILL",
    "weight": 1.0,
    "properties": {}
  },
  {
    "source_id": "student_n06114515",
    "target_id": "skill_data_science_(pandas,_numpy,_sql)",
    "relation_type": "HAS_SKILL",
    "weight": 1.0,
    "properties": {}
  },
  {
    "source_id": "student_n06114515",
    "target_id": "skill_networking_protocols_(tcp/ip,_udp)",
    "relation_type": "HAS_SKILL",
    "weight": 1.0,
    "properties": {}
  },
  {
    "source_id": "student_n06114515",
    "target_id": "skill_python_programming",
    "relation_type": "HAS_SKILL",
    "weight": 1.0,
    "properties": {}
  },
  {
    "source_id": "student_n06114515",
    "target_id": "skill_java_(object-oriented_design)",
    "relation_type": "HAS_SKILL",
    "weight": 1.0,
    "properties": {}
  },
  {
    "source_id": "student_n06114515",
    "target_id": "skill_data_visualization_(matplotlib,_tableau)",
    "relation_type": "HAS_SKILL",
    "weight": 1.0,
    "properties": {}
  },
  {
    "source_id": "student_n06114515",
    "target_id": "skill_cloud_computing_(aws_basics)",
    "relation_type": "HAS_SKILL",
    "weight": 1.0,
    "properties": {}
  },
  {
    "source_id": "student_n06114515",
    "target_id": "skill_git_and_version_control",
    "relation_type": "HAS_SKILL",
    "weight": 1.0,
    "properties": {}
  },
  {
    "source_id": "student_n06114515",
    "target_id": "interest_artificial_intelligence",
    "relation_type": "INTERESTED_IN",
    "weight": 1.0,
    "properties": {}
  },
  {
    "source_id": "student_n06114515",
    "target_id": "interest_geospatial_data_analysis",
    "relation_type": "INTERESTED_IN",
    "weight": 1.0,
    "properties": {}
  },
  {
    "source_id": "student_n06114515",
    "target_id": "interest_network_optimization",
    "relation_type": "INTERESTED_IN",
    "weight": 1.0,
    "properties": {}
  },
  {
    "source_id": "student_n06114515",
    "target_id": "interest_open-source_software_development",
    "relation_type": "INTERESTED_IN",
    "weight": 1.0,
    "properties": {}
  },
  {
    "source_id": "student_n06114515",
    "target_id": "interest_scientific_computing",
    "relation_type": "INTERESTED_IN",
    "weight": 1.0,
    "properties": {}
  }
]