[
  {
    "id": "student_n10995912",
    "name": "Rowan Moore",
    "entity_type": "STUDENT",
    "properties": {
      "student_id": "n10995912",
      "major": "Software Development",
      "year": "3rd Year",
      "file_path": "profile_md/IFN712 Project Proposal Template_2025_Feng_V2P/n10995912_Rowan_Moore.md"
    }
  },
  {
    "id": "major_software_development",
    "name": "Software Development",
    "entity_type": "MAJOR",
    "properties": {}
  },
  {
    "id": "course_ifn666_web_technologies",
    "name": "IFN666 Web Technologies",
    "entity_type": "COURSE",
    "properties": {}
  },
  {
    "id": "course_ifn554_databases",
    "name": "IFN554 Databases",
    "entity_type": "COURSE",
    "properties": {}
  },
  {
    "id": "course_ifn553_introduction_to_security_and_networking",
    "name": "IFN553 Introduction to Security and Networking",
    "entity_type": "COURSE",
    "properties": {}
  },
  {
    "id": "course_ifn670_mobile_application_development",
    "name": "IFN670 Mobile Application Development",
    "entity_type": "COURSE",
    "properties": {}
  },
  {
    "id": "course_ifn556_object_oriented_programming",
    "name": "IFN556 Object Oriented Programming",
    "entity_type": "COURSE",
    "properties": {}
  },
  {
    "id": "course_ifn668_advanced_software_engineering",
    "name": "IFN668 Advanced Software Engineering",
    "entity_type": "COURSE",
    "properties": {}
  },
  {
    "id": "course_ifn552_systems_analysis_and_design",
    "name": "IFN552 Systems Analysis and Design",
    "entity_type": "COURSE",
    "properties": {}
  },
  {
    "id": "course_ifn555_introduction_to_programming",
    "name": "IFN555 Introduction to Programming",
    "entity_type": "COURSE",
    "properties": {}
  },
  {
    "id": "skill_web_development_(react,_node.js,_angular)",
    "name": "Web development (React, Node.js, Angular)",
    "entity_type": "SKILL",
    "properties": {}
  },
  {
    "id": "skill_mobile_development_(kotlin,_swift,_react_native)",
    "name": "Mobile development (Kotlin, Swift, React Native)",
    "entity_type": "SKILL",
    "properties": {}
  },
  {
    "id": "skill_database_design_(sql,_mongodb)",
    "name": "Database design (SQL, MongoDB)",
    "entity_type": "SKILL",
    "properties": {}
  },
  {
    "id": "skill_cybersecurity_(encryption,_api_security)",
    "name": "Cybersecurity (encryption, API security)",
    "entity_type": "SKILL",
    "properties": {}
  },
  {
    "id": "skill_networking_protocols_(tcp/ip,_restful_apis)",
    "name": "Networking protocols (TCP/IP, RESTful APIs)",
    "entity_type": "SKILL",
    "properties": {}
  },
  {
    "id": "skill_data_science_(python,_pandas,_data_visualization)",
    "name": "Data science (Python, Pandas, data visualization)",
    "entity_type": "SKILL",
    "properties": {}
  },
  {
    "id": "skill_version_control_(git,_github)",
    "name": "Version control (Git, GitHub)",
    "entity_type": "SKILL",
    "properties": {}
  },
  {
    "id": "skill_cloud_platforms_(aws,_azure)",
    "name": "Cloud platforms (AWS, Azure)",
    "entity_type": "SKILL",
    "properties": {}
  },
  {
    "id": "interest_open-source_software_development",
    "name": "Open-source software development",
    "entity_type": "INTEREST",
    "properties": {}
  },
  {
    "id": "interest_cybersecurity_research",
    "name": "Cybersecurity research",
    "entity_type": "INTEREST",
    "properties": {}
  },
  {
    "id": "interest_internet_of_things_(iot)_applications",
    "name": "Internet of Things (IoT) applications",
    "entity_type": "INTEREST",
    "properties": {}
  },
  {
    "id": "interest_agile_software_methodologies",
    "name": "Agile software methodologies",
    "entity_type": "INTEREST",
    "properties": {}
  },
  {
    "id": "interest_urban_mobility_solutions",
    "name": "Urban mobility solutions",
    "entity_type": "INTEREST",
    "properties": {}
  }
]